pygments_portugol/__init__.py
pygments_portugol-0.2.1.dist-info/LICENSE
pygments_portugol-0.2.1.dist-info/METADATA
pygments_portugol-0.2.1.dist-info/WHEEL
pygments_portugol-0.2.1.dist-info/entry_points.txt
pygments_portugol-0.2.1.dist-info/top_level.txt
pygments_portugol-0.2.1.dist-info/RECORD
