Metadata-Version: 2.1
Name: pygments-portugol
Version: 0.2.1
Summary: Pygments lexer for Portugol Studio.
Home-page: https://github.com/hellmrf/pygments-portugol
Author: Heliton Martins Reis Filho
Author-email: helitonmrf@gmail.com
License: GPLv3
Keywords: pygments portugol studio lexer
Platform: UNKNOWN
Classifier: Development Status :: 4 - Beta
Classifier: Environment :: Plugins
Classifier: Intended Audience :: Developers
Classifier: License :: OSI Approved :: GNU General Public License v3 (GPLv3)
Classifier: Operating System :: OS Independent
Classifier: Programming Language :: Python
Classifier: Programming Language :: Python :: 2
Classifier: Programming Language :: Python :: 3
Classifier: Topic :: Software Development :: Libraries :: Python Modules
Classifier: Natural Language :: Portuguese (Brazilian)
License-File: LICENSE
Requires-Dist: pygments (>=2.0)
